tatu/__init__.py
tatu/amnesia.py
tatu/auth.py
tatu/disk.py
tatu/okast.py
tatu/okatest.py
tatu/pickle_.py
tatu/rsyncserver.py
tatu/storageinterface.py
tatu/test_okast.py
tatu/abs/__init__.py
tatu/abs/sql.py
tatu/abs/sqlreadonly.py
tatu/abs/storage.py
tatu/abs/mixin/__init__.py
tatu/abs/mixin/setup.py
tatu/abs/mixin/thread.py
tatu/main/__init__.py
tatu/main/test_Tatu.py
tatu/sql/__init__.py
tatu/sql/mysql.py
tatu/sql/sqla.py
tatu/sql/sqlite.py
tatu/sql/test_sqla.py
tatu-0.2107.26.dist-info/LICENSE
tatu-0.2107.26.dist-info/METADATA
tatu-0.2107.26.dist-info/WHEEL
tatu-0.2107.26.dist-info/top_level.txt
tatu-0.2107.26.dist-info/RECORD
