Metadata-Version: 2.1
Name: tatu
Version: 0.2107.26
Summary: Persistent Science
Home-page: https://github.com/davips/tatu
Author: Davi Pereira dos Santos
Author-email: dpsbac@gmail.com
License: GPL3
Download-URL: https://github.com/davips/tatu/releases
Platform: UNKNOWN
Classifier: Intended Audience :: Science/Research
Classifier: License :: OSI Approved :: GNU General Public License v3 (GPLv3)
Classifier: Natural Language :: English
Classifier: Programming Language :: Python
Classifier: Topic :: Scientific/Engineering
Classifier: Programming Language :: Python :: 3.8
Requires-Dist: numpy
Requires-Dist: sklearn
Requires-Dist: liac-arff
Requires-Dist: pymysql
Requires-Dist: aiuna (==0.2103.13)
Requires-Dist: requests
Requires-Dist: sqlalchemy
